fluttercraft/__init__.py
fluttercraft/__main__.py
fluttercraft/main.py
fluttercraft/commands/__init__.py
fluttercraft/commands/command_handler.py
fluttercraft/commands/flutter_commands.py
fluttercraft/commands/fvm_commands.py
fluttercraft/commands/help_commands.py
fluttercraft/commands/start.py
fluttercraft/commands/flutter/__init__.py
fluttercraft/commands/flutter/version.py
fluttercraft/commands/fvm/__init__.py
fluttercraft/commands/fvm/install.py
fluttercraft/commands/fvm/list.py
fluttercraft/commands/fvm/releases.py
fluttercraft/commands/fvm/uninstall.py
fluttercraft/commands/fvm/version.py
fluttercraft/commands/help/__init__.py
fluttercraft/commands/help/common.py
fluttercraft/commands/help/fvm_help.py
fluttercraft/commands/help/global_help.py
fluttercraft/commands/help/handler.py
fluttercraft/config/__init__.py
fluttercraft/utils/__init__.py
fluttercraft/utils/beautiful_display.py
fluttercraft/utils/beautiful_prompt.py
fluttercraft/utils/display_utils.py
fluttercraft/utils/platform_utils.py
fluttercraft/utils/system_utils.py
fluttercraft/utils/terminal_utils.py
fluttercraft-0.1.2.dist-info/licenses/LICENSE
fluttercraft-0.1.2.dist-info/METADATA
fluttercraft-0.1.2.dist-info/WHEEL
fluttercraft-0.1.2.dist-info/entry_points.txt
fluttercraft-0.1.2.dist-info/top_level.txt
fluttercraft-0.1.2.dist-info/RECORD
