Metadata-Version: 2.4
Name: fluttercraft
Version: 0.1.2
Summary: Automate your Flutter app setup like a pro
Home-page: https://github.com/UTTAM-VAGHASIA/fluttercraft
Author: UTTAM-VAGHASIA
Classifier: Development Status :: 3 - Alpha
Classifier: Intended Audience :: Developers
Classifier: Programming Language :: Python :: 3
Classifier: License :: OSI Approved :: GNU Affero General Public License v3
Classifier: Operating System :: OS Independent
Requires-Python: >=3.10
License-File: LICENSE
Requires-Dist: typer[all]
Requires-Dist: pyfiglet
Requires-Dist: colorama
Requires-Dist: rich
Requires-Dist: prompt_toolkit>=3.0.0
Requires-Dist: pygments>=2.0.0
Dynamic: author
Dynamic: classifier
Dynamic: description
Dynamic: description-content-type
Dynamic: home-page
Dynamic: license-file
Dynamic: requires-dist
Dynamic: requires-python
Dynamic: summary
